[
    {
        "color": "#bfb87f",
        "id": 1,
        "identifier": "Normal"
    },
    {
        "color": "#d32f2f",
        "id": 2,
        "identifier": "Fighting"
    },
    {
        "color": "#9d87e0",
        "id": 3,
        "identifier": "Flying"
    },
    {
        "color": "#ab47bc",
        "id": 4,
        "identifier": "Poison"
    },
    {
        "color": "#e0b352",
        "id": 5,
        "identifier": "Ground"
    },
    {
        "color": "#bda537",
        "id": 6,
        "identifier": "Rock"
    },
    {
        "color": "#98b82d",
        "id": 7,
        "identifier": "Bug"
    },
    {
        "color": "#7556a5",
        "id": 8,
        "identifier": "Ghost"
    },
    {
        "color": "#b4b4cc",
        "id": 9,
        "identifier": "Steel"
    },
    {
        "color": "#e86513",
        "id": 10,
        "identifier": "Fire"
    },
    {
        "color": "#2196f3",
        "id": 11,
        "identifier": "Water"
    },
    {
        "color": "#4caf50",
        "id": 12,
        "identifier": "Grass"
    },
    {
        "color": "#ffcc08",
        "id": 13,
        "identifier": "Electric"
    },
    {
        "color": "#ec407a",
        "id": 14,
        "identifier": "Psychic"
    },
    {
        "color": "#80deea",
        "id": 15,
        "identifier": "Ice"
    },
    {
        "color": "#673ab7",
        "id": 16,
        "identifier": "Dragon"
    },
    {
        "color": "#5d4037",
        "id": 17,
        "identifier": "Dark"
    },
    {
        "color": "#f483bb",
        "id": 18,
        "identifier": "Fairy"
    },
    {
        "color": "#ffffff",
        "id": 10001,
        "identifier": "Unknown"
    },
    {
        "color": "#ffffff",
        "id": 10002,
        "identifier": "Shadow"
    }
]
